LICENSE
MANIFEST.in
README.rst
requirements.txt
setup.py
winger.py
winger.egg-info/PKG-INFO
winger.egg-info/SOURCES.txt
winger.egg-info/dependency_links.txt
winger.egg-info/requires.txt
winger.egg-info/top_level.txt