Metadata-Version: 1.1
Name: winger
Version: 0.0.1
Summary: A Python3 module defines dict-like classes to handle Windows registry
Home-page: https://github.com/meng89/winger
Author: Chen Meng
Author-email: ObserverChan@gmail.com
License: LGPL v3.0
Platform: UNKNOWN
Classifier: Intended Audience :: Developers
Classifier: License :: OSI Approved :: GNU Library or Lesser General Public License (LGPL)
Classifier: Operating System :: Microsoft :: Windows
Classifier: Programming Language :: Python :: 3
Classifier: Topic :: Software Development :: Libraries :: Python Modules
